richbibtext/__init__.py
richbibtext-0.1.4.dist-info/METADATA
richbibtext-0.1.4.dist-info/WHEEL
richbibtext-0.1.4.dist-info/RECORD
