Metadata-Version: 2.1
Name: richbibtext
Version: 0.1.4
Summary: 
Author: rebuglio
Author-email: m.rebuglio@gmail.com
Requires-Python: >=3.11,<4.0
Classifier: Programming Language :: Python :: 3
Classifier: Programming Language :: Python :: 3.11
Classifier: Programming Language :: Python :: 3.12
Requires-Dist: bibtexparser (==2.0.0b3)
